[
    {
        "ArchStdEvent": "MEM_ACCESS"
    },
    {
        "ArchStdEvent": "REMOTE_ACCESS_RD"
    },
    {
        "ArchStdEvent": "MEM_ACCESS_RD"
    },
    {
        "ArchStdEvent": "MEM_ACCESS_WR"
    },
    {
        "ArchStdEvent": "LDST_ALIGN_LAT"
    },
    {
        "ArchStdEvent": "LD_ALIGN_LAT"
    },
    {
        "ArchStdEvent": "ST_ALIGN_LAT"
    },
    {
        "ArchStdEvent": "MEM_ACCESS_CHECKED"
    },
    {
        "ArchStdEvent": "MEM_ACCESS_CHECKED_RD"
    },
    {
        "ArchStdEvent": "MEM_ACCESS_CHECKED_WR"
    }
]
