[
    {
        "BriefDescription": "This event is deprecated. Refer to new event ARITH.DIV_ACTIVE",
        "Counter": "0,1,2,3,4,5,6,7",
        "CounterMask": "1",
        "Deprecated": "1",
        "EventCode": "0xb0",
        "EventName": "ARITH.DIVIDER_ACTIVE",
        "SampleAfterValue": "1000003",
        "UMask": "0x9",
        "Unit": "cpu_core"
    },
    {
        "BriefDescription": "Counts the number of cycles when any of the floating point or integer dividers are active.",
        "Counter": "0,1,2,3,4,5",
        "CounterMask": "1",
        "EventCode": "0xcd",
        "EventName": "ARITH.DIV_ACTIVE",
        "SampleAfterValue": "1000003",
        "UMask": "0x3",
        "Unit": "cpu_atom"
    },
    {
        "BriefDescription": "Cycles when divide unit is busy executing divide or square root operations.",
        "Counter": "0,1,2,3,4,5,6,7",
        "CounterMask": "1",
        "EventCode": "0xb0",
        "EventName": "ARITH.DIV_ACTIVE",
        "PublicDescription": "Counts cycles when divide unit is busy executing divide or square root operations. Accounts for integer and floating-point operations.",
        "SampleAfterValue": "1000003",
        "UMask": "0x9",
        "Unit": "cpu_core"
    },
    {
        "BriefDescription": "Counts the number of active floating point and integer dividers per cycle.",
        "Counter": "0,1,2,3,4,5",
        "EventCode": "0xcd",
        "EventName": "ARITH.DIV_OCCUPANCY",
        "SampleAfterValue": "1000003",
        "UMask": "0x3",
        "Unit": "cpu_atom"
    },
    {
        "BriefDescription": "Counts the number of floating point and integer divider uops executed per cycle.",
        "Counter": "0,1,2,3,4,5",
        "EventCode": "0xcd",
        "EventName": "ARITH.DIV_UOPS",
        "SampleAfterValue": "1000003",
        "UMask": "0xc",
        "Unit": "cpu_atom"
    },
    {
        "BriefDescription": "This event is deprecated. Refer to new event ARITH.FPDIV_ACTIVE",
        "Counter": "0,1,2,3,4,5,6,7",
        "CounterMask": "1",
        "Deprecated": "1",
        "EventCode": "0xb0",
        "EventName": "ARITH.FP_DIVIDER_ACTIVE",
        "SampleAfterValue": "1000003",
        "UMask": "0x1",
        "Unit": "cpu_core"
    },
    {
        "BriefDescription": "Counts the number of cycles any of the two integer dividers are active.",
        "Counter": "0,1,2,3,4,5",
        "CounterMask": "1",
        "EventCode": "0xcd",
        "EventName": "ARITH.IDIV_ACTIVE",
        "SampleAfterValue": "1000003",
        "UMask": "0x1",
        "Unit": "cpu_atom"
    },
    {
        "BriefDescription": "This event counts the cycles the integer divider is busy.",
        "Counter": "0,1,2,3,4,5,6,7",
        "CounterMask": "1",
        "EventCode": "0xb0",
        "EventName": "ARITH.IDIV_ACTIVE",
        "SampleAfterValue": "1000003",
        "UMask": "0x8",
        "Unit": "cpu_core"
    },
    {
        "BriefDescription": "Counts the number of active integer dividers per cycle.",
        "Counter": "0,1,2,3,4,5",
        "EventCode": "0xcd",
        "EventName": "ARITH.IDIV_OCCUPANCY",
        "SampleAfterValue": "1000003",
        "UMask": "0x1",
        "Unit": "cpu_atom"
    },
    {
        "BriefDescription": "Counts the number of integer divider uops executed per cycle.",
        "Counter": "0,1,2,3,4,5",
        "EventCode": "0xcd",
        "EventName": "ARITH.IDIV_UOPS",
        "SampleAfterValue": "1000003",
        "UMask": "0x4",
        "Unit": "cpu_atom"
    },
    {
        "BriefDescription": "This event is deprecated. Refer to new event ARITH.IDIV_ACTIVE",
        "Counter": "0,1,2,3,4,5,6,7",
        "CounterMask": "1",
        "Deprecated": "1",
        "EventCode": "0xb0",
        "EventName": "ARITH.INT_DIVIDER_ACTIVE",
        "SampleAfterValue": "1000003",
        "UMask": "0x8",
        "Unit": "cpu_core"
    },
    {
        "BriefDescription": "Number of occurrences where a microcode assist is invoked by hardware.",
        "Counter": "0,1,2,3,4,5,6,7",
        "EventCode": "0xc1",
        "EventName": "ASSISTS.ANY",
        "PublicDescription": "Counts the number of occurrences where a microcode assist is invoked by hardware. Examples include AD (page Access Dirty), FP and AVX related assists.",
        "SampleAfterValue": "100003",
        "UMask": "0x1b",
        "Unit": "cpu_core"
    },
    {
        "BriefDescription": "Counts the total number of branch instructions retired for all branch types.",
        "Counter": "0,1,2,3,4,5",
        "EventCode": "0xc4",
        "EventName": "BR_INST_RETIRED.ALL_BRANCHES",
        "PublicDescription": "Counts the total number of instructions in which the instruction pointer (IP) of the processor is resteered due to a branch instruction and the branch instruction successfully retires.  All branch type instructions are accounted for.",
        "SampleAfterValue": "200003",
        "Unit": "cpu_atom"
    },
    {
        "BriefDescription": "All branch instructions retired.",
        "Counter": "0,1,2,3,4,5,6,7",
        "EventCode": "0xc4",
        "EventName": "BR_INST_RETIRED.ALL_BRANCHES",
        "PublicDescription": "Counts all branch instructions retired. Available PDIST counters: 0",
        "SampleAfterValue": "400009",
        "Unit": "cpu_core"
    },
    {
        "BriefDescription": "This event is deprecated. Refer to new event BR_INST_RETIRED.NEAR_CALL",
        "Counter": "0,1,2,3,4,5",
        "Deprecated": "1",
        "EventCode": "0xc4",
        "EventName": "BR_INST_RETIRED.CALL",
        "SampleAfterValue": "200003",
        "UMask": "0xf9",
        "Unit": "cpu_atom"
    },
    {
        "BriefDescription": "Counts the number of retired JCC (Jump on Conditional Code) branch instructions retired, includes both taken and not taken branches.",
        "Counter": "0,1,2,3,4,5",
        "EventCode": "0xc4",
        "EventName": "BR_INST_RETIRED.COND",
        "SampleAfterValue": "200003",
        "UMask": "0x7e",
        "Unit": "cpu_atom"
    },
    {
        "BriefDescription": "Conditional branch instructions retired.",
        "Counter": "0,1,2,3,4,5,6,7",
        "EventCode": "0xc4",
        "EventName": "BR_INST_RETIRED.COND",
        "PublicDescription": "Counts conditional branch instructions retired. Available PDIST counters: 0",
        "SampleAfterValue": "400009",
        "UMask": "0x11",
        "Unit": "cpu_core"
    },
    {
        "BriefDescription": "Not taken branch instructions retired.",
        "Counter": "0,1,2,3,4,5,6,7",
        "EventCode": "0xc4",
        "EventName": "BR_INST_RETIRED.COND_NTAKEN",
        "PublicDescription": "Counts not taken branch instructions retired. Available PDIST counters: 0",
        "SampleAfterValue": "400009",
        "UMask": "0x10",
        "Unit": "cpu_core"
    },
    {
        "BriefDescription": "Counts the number of taken JCC (Jump on Conditional Code) branch instructions retired.",
        "Counter": "0,1,2,3,4,5",
        "EventCode": "0xc4",
        "EventName": "BR_INST_RETIRED.COND_TAKEN",
        "SampleAfterValue": "200003",
        "UMask": "0xfe",
        "Unit": "cpu_atom"
    },
    {
        "BriefDescription": "Taken conditional branch instructions retired.",
        "Counter": "0,1,2,3,4,5,6,7",
        "EventCode": "0xc4",
        "EventName": "BR_INST_RETIRED.COND_TAKEN",
        "PublicDescription": "Counts taken conditional branch instructions retired. Available PDIST counters: 0",
        "SampleAfterValue": "400009",
        "UMask": "0x1",
        "Unit": "cpu_core"
    },
    {
        "BriefDescription": "Counts the number of far branch instructions retired, includes far jump, far call and return, and interrupt call and return.",
        "Counter": "0,1,2,3,4,5",
        "EventCode": "0xc4",
        "EventName": "BR_INST_RETIRED.FAR_BRANCH",
        "SampleAfterValue": "200003",
        "UMask": "0xbf",
        "Unit": "cpu_atom"
    },
    {
        "BriefDescription": "Far branch instructions retired.",
        "Counter": "0,1,2,3,4,5,6,7",
        "EventCode": "0xc4",
        "EventName": "BR_INST_RETIRED.FAR_BRANCH",
        "PublicDescription": "Counts far branch instructions retired. Available PDIST counters: 0",
        "SampleAfterValue": "100007",
        "UMask": "0x40",
        "Unit": "cpu_core"
    },
    {
        "BriefDescription": "Counts the number of near indirect JMP and near indirect CALL branch instructions retired.",
        "Counter": "0,1,2,3,4,5",
        "EventCode": "0xc4",
        "EventName": "BR_INST_RETIRED.INDIRECT",
        "SampleAfterValue": "200003",
        "UMask": "0xeb",
        "Unit": "cpu_atom"
    },
    {
        "BriefDescription": "Indirect near branch instructions retired (excluding returns)",
        "Counter": "0,1,2,3,4,5,6,7",
        "EventCode": "0xc4",
        "EventName": "BR_INST_RETIRED.INDIRECT",
        "PublicDescription": "Counts near indirect branch instructions retired excluding returns. TSX abort is an indirect branch. Available PDIST counters: 0",
        "SampleAfterValue": "100003",
        "UMask": "0x80",
        "Unit": "cpu_core"
    },
    {
        "BriefDescription": "Counts the number of near indirect CALL branch instructions retired.",
        "Counter": "0,1,2,3,4,5",
        "EventCode": "0xc4",
        "EventName": "BR_INST_RETIRED.INDIRECT_CALL",
        "SampleAfterValue": "200003",
        "UMask": "0xfb",
        "Unit": "cpu_atom"
    },
    {
        "BriefDescription": "This event is deprecated. Refer to new event BR_INST_RETIRED.INDIRECT_CALL",
        "Counter": "0,1,2,3,4,5",
        "Deprecated": "1",
        "EventCode": "0xc4",
        "EventName": "BR_INST_RETIRED.IND_CALL",
        "SampleAfterValue": "200003",
        "UMask": "0xfb",
        "Unit": "cpu_atom"
    },
    {
        "BriefDescription": "This event is deprecated. Refer to new event BR_INST_RETIRED.COND",
        "Counter": "0,1,2,3,4,5",
        "Deprecated": "1",
        "EventCode": "0xc4",
        "EventName": "BR_INST_RETIRED.JCC",
        "SampleAfterValue": "200003",
        "UMask": "0x7e",
        "Unit": "cpu_atom"
    },
    {
        "BriefDescription": "Counts the number of near CALL branch instructions retired.",
        "Counter": "0,1,2,3,4,5",
        "EventCode": "0xc4",
        "EventName": "BR_INST_RETIRED.NEAR_CALL",
        "SampleAfterValue": "200003",
        "UMask": "0xf9",
        "Unit": "cpu_atom"
    },
    {
        "BriefDescription": "Direct and indirect near call instructions retired.",
        "Counter": "0,1,2,3,4,5,6,7",
        "EventCode": "0xc4",
        "EventName": "BR_INST_RETIRED.NEAR_CALL",
        "PublicDescription": "Counts both direct and indirect near call instructions retired. Available PDIST counters: 0",
        "SampleAfterValue": "100007",
        "UMask": "0x2",
        "Unit": "cpu_core"
    },
    {
        "BriefDescription": "Counts the number of near RET branch instructions retired.",
        "Counter": "0,1,2,3,4,5",
        "EventCode": "0xc4",
        "EventName": "BR_INST_RETIRED.NEAR_RETURN",
        "SampleAfterValue": "200003",
        "UMask": "0xf7",
        "Unit": "cpu_atom"
    },
    {
        "BriefDescription": "Return instructions retired.",
        "Counter": "0,1,2,3,4,5,6,7",
        "EventCode": "0xc4",
        "EventName": "BR_INST_RETIRED.NEAR_RETURN",
        "PublicDescription": "Counts return instructions retired. Available PDIST counters: 0",
        "SampleAfterValue": "100007",
        "UMask": "0x8",
        "Unit": "cpu_core"
    },
    {
        "BriefDescription": "Counts the number of near taken branch instructions retired.",
        "Counter": "0,1,2,3,4,5",
        "EventCode": "0xc4",
        "EventName": "BR_INST_RETIRED.NEAR_TAKEN",
        "SampleAfterValue": "200003",
        "UMask": "0xc0",
        "Unit": "cpu_atom"
    },
    {
        "BriefDescription": "Taken branch instructions retired.",
        "Counter": "0,1,2,3,4,5,6,7",
        "EventCode": "0xc4",
        "EventName": "BR_INST_RETIRED.NEAR_TAKEN",
        "PublicDescription": "Counts taken branch instructions retired. Available PDIST counters: 0",
        "SampleAfterValue": "400009",
        "UMask": "0x20",
        "Unit": "cpu_core"
    },
    {
        "BriefDescription": "This event is deprecated. Refer to new event BR_INST_RETIRED.INDIRECT",
        "Counter": "0,1,2,3,4,5",
        "Deprecated": "1",
        "EventCode": "0xc4",
        "EventName": "BR_INST_RETIRED.NON_RETURN_IND",
        "SampleAfterValue": "200003",
        "UMask": "0xeb",
        "Unit": "cpu_atom"
    },
    {
        "BriefDescription": "Counts the number of near relative CALL branch instructions retired.",
        "Counter": "0,1,2,3,4,5",
        "EventCode": "0xc4",
        "EventName": "BR_INST_RETIRED.REL_CALL",
        "SampleAfterValue": "200003",
        "UMask": "0xfd",
        "Unit": "cpu_atom"
    },
    {
        "BriefDescription": "This event is deprecated. Refer to new event BR_INST_RETIRED.NEAR_RETURN",
        "Counter": "0,1,2,3,4,5",
        "Deprecated": "1",
        "EventCode": "0xc4",
        "EventName": "BR_INST_RETIRED.RETURN",
        "SampleAfterValue": "200003",
        "UMask": "0xf7",
        "Unit": "cpu_atom"
    },
    {
        "BriefDescription": "This event is deprecated. Refer to new event BR_INST_RETIRED.COND_TAKEN",
        "Counter": "0,1,2,3,4,5",
        "Deprecated": "1",
        "EventCode": "0xc4",
        "EventName": "BR_INST_RETIRED.TAKEN_JCC",
        "SampleAfterValue": "200003",
        "UMask": "0xfe",
        "Unit": "cpu_atom"
    },
    {
        "BriefDescription": "Counts the total number of mispredicted branch instructions retired for all branch types.",
        "Counter": "0,1,2,3,4,5",
        "EventCode": "0xc5",
        "EventName": "BR_MISP_RETIRED.ALL_BRANCHES",
        "PublicDescription": "Counts the total number of mispredicted branch instructions retired.  All branch type instructions are accounted for.  Prediction of the branch target address enables the processor to begin executing instructions before the non-speculative execution path is known. The branch prediction unit (BPU) predicts the target address based on the instruction pointer (IP) of the branch and on the execution path through which execution reached this IP.    A branch misprediction occurs when the prediction is wrong, and results in discarding all instructions executed in the speculative path and re-fetching from the correct path.",
        "SampleAfterValue": "200003",
        "Unit": "cpu_atom"
    },
    {
        "BriefDescription": "All mispredicted branch instructions retired.",
        "Counter": "0,1,2,3,4,5,6,7",
        "EventCode": "0xc5",
        "EventName": "BR_MISP_RETIRED.ALL_BRANCHES",
        "PublicDescription": "Counts all the retired branch instructions that were mispredicted by the processor. A branch misprediction occurs when the processor incorrectly predicts the destination of the branch.  When the misprediction is discovered at execution, all the instructions executed in the wrong (speculative) path must be discarded, and the processor must start fetching from the correct path. Available PDIST counters: 0",
        "SampleAfterValue": "400009",
        "Unit": "cpu_core"
    },
    {
        "BriefDescription": "Counts the number of mispredicted JCC (Jump on Conditional Code) branch instructions retired.",
        "Counter": "0,1,2,3,4,5",
        "EventCode": "0xc5",
        "EventName": "BR_MISP_RETIRED.COND",
        "SampleAfterValue": "200003",
        "UMask": "0x7e",
        "Unit": "cpu_atom"
    },
    {
        "BriefDescription": "Mispredicted conditional branch instructions retired.",
        "Counter": "0,1,2,3,4,5,6,7",
        "EventCode": "0xc5",
        "EventName": "BR_MISP_RETIRED.COND",
        "PublicDescription": "Counts mispredicted conditional branch instructions retired. Available PDIST counters: 0",
        "SampleAfterValue": "400009",
        "UMask": "0x11",
        "Unit": "cpu_core"
    },
    {
        "BriefDescription": "Mispredicted non-taken conditional branch instructions retired.",
        "Counter": "0,1,2,3,4,5,6,7",
        "EventCode": "0xc5",
        "EventName": "BR_MISP_RETIRED.COND_NTAKEN",
        "PublicDescription": "Counts the number of conditional branch instructions retired that were mispredicted and the branch direction was not taken. Available PDIST counters: 0",
        "SampleAfterValue": "400009",
        "UMask": "0x10",
        "Unit": "cpu_core"
    },
    {
        "BriefDescription": "Counts the number of mispredicted taken JCC (Jump on Conditional Code) branch instructions retired.",
        "Counter": "0,1,2,3,4,5",
        "EventCode": "0xc5",
        "EventName": "BR_MISP_RETIRED.COND_TAKEN",
        "SampleAfterValue": "200003",
        "UMask": "0xfe",
        "Unit": "cpu_atom"
    },
    {
        "BriefDescription": "number of branch instructions retired that were mispredicted and taken.",
        "Counter": "0,1,2,3,4,5,6,7",
        "EventCode": "0xc5",
        "EventName": "BR_MISP_RETIRED.COND_TAKEN",
        "PublicDescription": "Counts taken conditional mispredicted branch instructions retired. Available PDIST counters: 0",
        "SampleAfterValue": "400009",
        "UMask": "0x1",
        "Unit": "cpu_core"
    },
    {
        "BriefDescription": "Counts the number of mispredicted near indirect JMP and near indirect CALL branch instructions retired.",
        "Counter": "0,1,2,3,4,5",
        "EventCode": "0xc5",
        "EventName": "BR_MISP_RETIRED.INDIRECT",
        "SampleAfterValue": "200003",
        "UMask": "0xeb",
        "Unit": "cpu_atom"
    },
    {
        "BriefDescription": "Miss-predicted near indirect branch instructions retired (excluding returns)",
        "Counter": "0,1,2,3,4,5,6,7",
        "EventCode": "0xc5",
        "EventName": "BR_MISP_RETIRED.INDIRECT",
        "PublicDescription": "Counts miss-predicted near indirect branch instructions retired excluding returns. TSX abort is an indirect branch. Available PDIST counters: 0",
        "SampleAfterValue": "100003",
        "UMask": "0x80",
        "Unit": "cpu_core"
    },
    {
        "BriefDescription": "Counts the number of mispredicted near indirect CALL branch instructions retired.",
        "Counter": "0,1,2,3,4,5",
        "EventCode": "0xc5",
        "EventName": "BR_MISP_RETIRED.INDIRECT_CALL",
        "SampleAfterValue": "200003",
        "UMask": "0xfb",
        "Unit": "cpu_atom"
    },
    {
        "BriefDescription": "Mispredicted indirect CALL retired.",
        "Counter": "0,1,2,3,4,5,6,7",
        "EventCode": "0xc5",
        "EventName": "BR_MISP_RETIRED.INDIRECT_CALL",
        "PublicDescription": "Counts retired mispredicted indirect (near taken) CALL instructions, including both register and memory indirect. Available PDIST counters: 0",
        "SampleAfterValue": "400009",
        "UMask": "0x2",
        "Unit": "cpu_core"
    },
    {
        "BriefDescription": "This event is deprecated. Refer to new event BR_MISP_RETIRED.INDIRECT_CALL",
        "Counter": "0,1,2,3,4,5",
        "Deprecated": "1",
        "EventCode": "0xc5",
        "EventName": "BR_MISP_RETIRED.IND_CALL",
        "SampleAfterValue": "200003",
        "UMask": "0xfb",
        "Unit": "cpu_atom"
    },
    {
        "BriefDescription": "This event is deprecated. Refer to new event BR_MISP_RETIRED.COND",
        "Counter": "0,1,2,3,4,5",
        "Deprecated": "1",
        "EventCode": "0xc5",
        "EventName": "BR_MISP_RETIRED.JCC",
        "SampleAfterValue": "200003",
        "UMask": "0x7e",
        "Unit": "cpu_atom"
    },
    {
        "BriefDescription": "Counts the number of mispredicted near taken branch instructions retired.",
        "Counter": "0,1,2,3,4,5",
        "EventCode": "0xc5",
        "EventName": "BR_MISP_RETIRED.NEAR_TAKEN",
        "SampleAfterValue": "200003",
        "UMask": "0x80",
        "Unit": "cpu_atom"
    },
    {
        "BriefDescription": "Number of near branch instructions retired that were mispredicted and taken.",
        "Counter": "0,1,2,3,4,5,6,7",
        "EventCode": "0xc5",
        "EventName": "BR_MISP_RETIRED.NEAR_TAKEN",
        "PublicDescription": "Counts number of near branch instructions retired that were mispredicted and taken. Available PDIST counters: 0",
        "SampleAfterValue": "400009",
        "UMask": "0x20",
        "Unit": "cpu_core"
    },
    {
        "BriefDescription": "This event is deprecated. Refer to new event BR_MISP_RETIRED.INDIRECT",
        "Counter": "0,1,2,3,4,5",
        "Deprecated": "1",
        "EventCode": "0xc5",
        "EventName": "BR_MISP_RETIRED.NON_RETURN_IND",
        "SampleAfterValue": "200003",
        "UMask": "0xeb",
        "Unit": "cpu_atom"
    },
    {
        "BriefDescription": "This event counts the number of mispredicted ret instructions retired. Non PEBS",
        "Counter": "0,1,2,3,4,5,6,7",
        "EventCode": "0xc5",
        "EventName": "BR_MISP_RETIRED.RET",
        "PublicDescription": "This is a non-precise version (that is, does not use PEBS) of the event that counts mispredicted return instructions retired. Available PDIST counters: 0",
        "SampleAfterValue": "100007",
        "UMask": "0x8",
        "Unit": "cpu_core"
    },
    {
        "BriefDescription": "Counts the number of mispredicted near RET branch instructions retired.",
        "Counter": "0,1,2,3,4,5",
        "EventCode": "0xc5",
        "EventName": "BR_MISP_RETIRED.RETURN",
        "SampleAfterValue": "200003",
        "UMask": "0xf7",
        "Unit": "cpu_atom"
    },
    {
        "BriefDescription": "This event is deprecated. Refer to new event BR_MISP_RETIRED.COND_TAKEN",
        "Counter": "0,1,2,3,4,5",
        "Deprecated": "1",
        "EventCode": "0xc5",
        "EventName": "BR_MISP_RETIRED.TAKEN_JCC",
        "SampleAfterValue": "200003",
        "UMask": "0xfe",
        "Unit": "cpu_atom"
    },
    {
        "BriefDescription": "Core clocks when the thread is in the C0.1 light-weight slower wakeup time but more power saving optimized state.",
        "Counter": "0,1,2,3,4,5,6,7",
        "EventCode": "0xec",
        "EventName": "CPU_CLK_UNHALTED.C01",
        "PublicDescription": "Counts core clocks when the thread is in the C0.1 light-weight slower wakeup time but more power saving optimized state.  This state can be entered via the TPAUSE or UMWAIT instructions.",
        "SampleAfterValue": "2000003",
        "UMask": "0x10",
        "Unit": "cpu_core"
    },
    {
        "BriefDescription": "Core clocks when the thread is in the C0.2 light-weight faster wakeup time but less power saving optimized state.",
        "Counter": "0,1,2,3,4,5,6,7",
        "EventCode": "0xec",
        "EventName": "CPU_CLK_UNHALTED.C02",
        "PublicDescription": "Counts core clocks when the thread is in the C0.2 light-weight faster wakeup time but less power saving optimized state.  This state can be entered via the TPAUSE or UMWAIT instructions.",
        "SampleAfterValue": "2000003",
        "UMask": "0x20",
        "Unit": "cpu_core"
    },
    {
        "BriefDescription": "Core clocks when the thread is in the C0.1 or C0.2 or running a PAUSE in C0 ACPI state.",
        "Counter": "0,1,2,3,4,5,6,7",
        "EventCode": "0xec",
        "EventName": "CPU_CLK_UNHALTED.C0_WAIT",
        "PublicDescription": "Counts core clocks when the thread is in the C0.1 or C0.2 power saving optimized states (TPAUSE or UMWAIT instructions) or running the PAUSE instruction.",
        "SampleAfterValue": "2000003",
        "UMask": "0x70",
        "Unit": "cpu_core"
    },
    {
        "BriefDescription": "Counts the number of unhalted core clock cycles. (Fixed event)",
        "Counter": "Fixed counter 1",
        "EventName": "CPU_CLK_UNHALTED.CORE",
        "PublicDescription": "Counts the number of core cycles while the core is not in a halt state. The core enters the halt state when it is running the HLT instruction. The core frequency may change from time to time. For this reason this event may have a changing ratio with regards to time. This event uses fixed counter 1.",
        "SampleAfterValue": "2000003",
        "UMask": "0x2",
        "Unit": "cpu_atom"
    },
    {
        "BriefDescription": "Counts the number of unhalted core clock cycles.",
        "Counter": "0,1,2,3,4,5",
        "EventCode": "0x3c",
        "EventName": "CPU_CLK_UNHALTED.CORE_P",
        "PublicDescription": "Counts the number of core cycles while the core is not in a halt state. The core enters the halt state when it is running the HLT instruction. The core frequency may change from time to time. For this reason this event may have a changing ratio with regards to time. This event uses a programmable general purpose performance counter.",
        "SampleAfterValue": "2000003",
        "Unit": "cpu_atom"
    },
    {
        "BriefDescription": "Cycle counts are evenly distributed between active threads in the Core.",
        "Counter": "0,1,2,3,4,5,6,7",
        "EventCode": "0xec",
        "EventName": "CPU_CLK_UNHALTED.DISTRIBUTED",
        "PublicDescription": "This event distributes cycle counts between active hyperthreads, i.e., those in C0.  A hyperthread becomes inactive when it executes the HLT or MWAIT instructions.  If all other hyperthreads are inactive (or disabled or do not exist), all counts are attributed to this hyperthread. To obtain the full count when the Core is active, sum the counts from each hyperthread.",
        "SampleAfterValue": "2000003",
        "UMask": "0x2",
        "Unit": "cpu_core"
    },
    {
        "BriefDescription": "Core crystal clock cycles when this thread is unhalted and the other thread is halted.",
        "Counter": "0,1,2,3,4,5,6,7",
        "EventCode": "0x3c",
        "EventName": "CPU_CLK_UNHALTED.ONE_THREAD_ACTIVE",
        "PublicDescription": "Counts Core crystal clock cycles when current thread is unhalted and the other thread is halted.",
        "SampleAfterValue": "25003",
        "UMask": "0x2",
        "Unit": "cpu_core"
    },
    {
        "BriefDescription": "CPU_CLK_UNHALTED.PAUSE",
        "Counter": "0,1,2,3,4,5,6,7",
        "EventCode": "0xec",
        "EventName": "CPU_CLK_UNHALTED.PAUSE",
        "SampleAfterValue": "2000003",
        "UMask": "0x40",
        "Unit": "cpu_core"
    },
    {
        "BriefDescription": "CPU_CLK_UNHALTED.PAUSE_INST",
        "Counter": "0,1,2,3,4,5,6,7",
        "CounterMask": "1",
        "EdgeDetect": "1",
        "EventCode": "0xec",
        "EventName": "CPU_CLK_UNHALTED.PAUSE_INST",
        "SampleAfterValue": "2000003",
        "UMask": "0x40",
        "Unit": "cpu_core"
    },
    {
        "BriefDescription": "This event is deprecated. Refer to new event CPU_CLK_UNHALTED.REF_TSC_P",
        "Counter": "0,1,2,3,4,5",
        "Deprecated": "1",
        "EventCode": "0x3c",
        "EventName": "CPU_CLK_UNHALTED.REF",
        "SampleAfterValue": "2000003",
        "UMask": "0x1",
        "Unit": "cpu_atom"
    },
    {
        "BriefDescription": "Core crystal clock cycles. Cycle counts are evenly distributed between active threads in the Core.",
        "Counter": "0,1,2,3,4,5,6,7",
        "EventCode": "0x3c",
        "EventName": "CPU_CLK_UNHALTED.REF_DISTRIBUTED",
        "PublicDescription": "This event distributes Core crystal clock cycle counts between active hyperthreads, i.e., those in C0 sleep-state. A hyperthread becomes inactive when it executes the HLT or MWAIT instructions. If one thread is active in a core, all counts are attributed to this hyperthread. To obtain the full count when the Core is active, sum the counts from each hyperthread.",
        "SampleAfterValue": "2000003",
        "UMask": "0x8",
        "Unit": "cpu_core"
    },
    {
        "BriefDescription": "Counts the number of unhalted reference clock cycles at TSC frequency. (Fixed event)",
        "Counter": "Fixed counter 2",
        "EventName": "CPU_CLK_UNHALTED.REF_TSC",
        "PublicDescription": "Counts the number of reference cycles that the core is not in a halt state. The core enters the halt state when it is running the HLT instruction. This event is not affected by core frequency changes and increments at a fixed frequency that is also used for the Time Stamp Counter (TSC). This event uses fixed counter 2.",
        "SampleAfterValue": "2000003",
        "UMask": "0x3",
        "Unit": "cpu_atom"
    },
    {
        "BriefDescription": "Reference cycles when the core is not in halt state.",
        "Counter": "Fixed counter 2",
        "EventName": "CPU_CLK_UNHALTED.REF_TSC",
        "PublicDescription": "Counts the number of reference cycles when the core is not in a halt state. The core enters the halt state when it is running the HLT instruction or the MWAIT instruction. This event is not affected by core frequency changes (for example, P states, TM2 transitions) but has the same incrementing frequency as the time stamp counter. This event can approximate elapsed time while the core was not in a halt state. It is counted on a dedicated fixed counter, leaving the eight programmable counters available for other events. Note: On all current platforms this event stops counting during 'throttling (TM)' states duty off periods the processor is 'halted'.  The counter update is done at a lower clock rate then the core clock the overflow status bit for this counter may appear 'sticky'.  After the counter has overflowed and software clears the overflow status bit and resets the counter to less than MAX. The reset value to the counter is not clocked immediately so the overflow status bit will flip 'high (1)' and generate another PMI (if enabled) after which the reset value gets clocked into the counter. Therefore, software will get the interrupt, read the overflow status bit '1 for bit 34 while the counter value is less than MAX. Software should ignore this case.",
        "SampleAfterValue": "2000003",
        "UMask": "0x3",
        "Unit": "cpu_core"
    },
    {
        "BriefDescription": "Counts the number of unhalted reference clock cycles at TSC frequency.",
        "Counter": "0,1,2,3,4,5",
        "EventCode": "0x3c",
        "EventName": "CPU_CLK_UNHALTED.REF_TSC_P",
        "PublicDescription": "Counts the number of reference cycles that the core is not in a halt state. The core enters the halt state when it is running the HLT instruction. This event is not affected by core frequency changes and increments at a fixed frequency that is also used for the Time Stamp Counter (TSC). This event uses a programmable general purpose performance counter.",
        "SampleAfterValue": "2000003",
        "UMask": "0x1",
        "Unit": "cpu_atom"
    },
    {
        "BriefDescription": "Reference cycles when the core is not in halt state.",
        "Counter": "0,1,2,3,4,5,6,7",
        "EventCode": "0x3c",
        "EventName": "CPU_CLK_UNHALTED.REF_TSC_P",
        "PublicDescription": "Counts the number of reference cycles when the core is not in a halt state. The core enters the halt state when it is running the HLT instruction or the MWAIT instruction. This event is not affected by core frequency changes (for example, P states, TM2 transitions) but has the same incrementing frequency as the time stamp counter. This event can approximate elapsed time while the core was not in a halt state. It is counted on a dedicated fixed counter, leaving the four (eight when Hyperthreading is disabled) programmable counters available for other events. Note: On all current platforms this event stops counting during 'throttling (TM)' states duty off periods the processor is 'halted'.  The counter update is done at a lower clock rate then the core clock the overflow status bit for this counter may appear 'sticky'.  After the counter has overflowed and software clears the overflow status bit and resets the counter to less than MAX. The reset value to the counter is not clocked immediately so the overflow status bit will flip 'high (1)' and generate another PMI (if enabled) after which the reset value gets clocked into the counter. Therefore, software will get the interrupt, read the overflow status bit '1 for bit 34 while the counter value is less than MAX. Software should ignore this case.",
        "SampleAfterValue": "2000003",
        "UMask": "0x1",
        "Unit": "cpu_core"
    },
    {
        "BriefDescription": "Counts the number of unhalted core clock cycles. (Fixed event)",
        "Counter": "Fixed counter 1",
        "EventName": "CPU_CLK_UNHALTED.THREAD",
        "PublicDescription": "Counts the number of core cycles while the core is not in a halt state.  The core enters the halt state when it is running the HLT instruction. The core frequency may change from time to time. For this reason this event may have a changing ratio with regards to time.  This event uses fixed counter 1.",
        "SampleAfterValue": "2000003",
        "UMask": "0x2",
        "Unit": "cpu_atom"
    },
    {
        "BriefDescription": "Core cycles when the thread is not in halt state",
        "Counter": "Fixed counter 1",
        "EventName": "CPU_CLK_UNHALTED.THREAD",
        "PublicDescription": "Counts the number of core cycles while the thread is not in a halt state. The thread enters the halt state when it is running the HLT instruction. This event is a component in many key event ratios. The core frequency may change from time to time due to transitions associated with Enhanced Intel SpeedStep Technology or TM2. For this reason this event may have a changing ratio with regards to time. When the core frequency is constant, this event can approximate elapsed time while the core was not in the halt state. It is counted on a dedicated fixed counter, leaving the eight programmable counters available for other events.",
        "SampleAfterValue": "2000003",
        "UMask": "0x2",
        "Unit": "cpu_core"
    },
    {
        "BriefDescription": "Counts the number of unhalted core clock cycles.",
        "Counter": "0,1,2,3,4,5",
        "EventCode": "0x3c",
        "EventName": "CPU_CLK_UNHALTED.THREAD_P",
        "PublicDescription": "Counts the number of core cycles while the core is not in a halt state.  The core enters the halt state when it is running the HLT instruction. The core frequency may change from time to time. For this reason this event may have a changing ratio with regards to time. This event uses a programmable general purpose performance counter.",
        "SampleAfterValue": "2000003",
        "Unit": "cpu_atom"
    },
    {
        "BriefDescription": "Thread cycles when thread is not in halt state",
        "Counter": "0,1,2,3,4,5,6,7",
        "EventCode": "0x3c",
        "EventName": "CPU_CLK_UNHALTED.THREAD_P",
        "PublicDescription": "This is an architectural event that counts the number of thread cycles while the thread is not in a halt state. The thread enters the halt state when it is running the HLT instruction. The core frequency may change from time to time due to power or thermal throttling. For this reason, this event may have a changing ratio with regards to wall clock time.",
        "SampleAfterValue": "2000003",
        "Unit": "cpu_core"
    },
    {
        "BriefDescription": "Cycles while L1 cache miss demand load is outstanding.",
        "Counter": "0,1,2,3",
        "CounterMask": "8",
        "EventCode": "0xa3",
        "EventName": "CYCLE_ACTIVITY.CYCLES_L1D_MISS",
        "SampleAfterValue": "1000003",
        "UMask": "0x8",
        "Unit": "cpu_core"
    },
    {
        "BriefDescription": "Cycles while L2 cache miss demand load is outstanding.",
        "Counter": "0,1,2,3",
        "CounterMask": "1",
        "EventCode": "0xa3",
        "EventName": "CYCLE_ACTIVITY.CYCLES_L2_MISS",
        "SampleAfterValue": "1000003",
        "UMask": "0x1",
        "Unit": "cpu_core"
    },
    {
        "BriefDescription": "Cycles while memory subsystem has an outstanding load.",
        "Counter": "0,1,2,3,4,5,6,7",
        "CounterMask": "16",
        "EventCode": "0xa3",
        "EventName": "CYCLE_ACTIVITY.CYCLES_MEM_ANY",
        "SampleAfterValue": "1000003",
        "UMask": "0x10",
        "Unit": "cpu_core"
    },
    {
        "BriefDescription": "Execution stalls while L1 cache miss demand load is outstanding.",
        "Counter": "0,1,2,3",
        "CounterMask": "12",
        "EventCode": "0xa3",
        "EventName": "CYCLE_ACTIVITY.STALLS_L1D_MISS",
        "SampleAfterValue": "1000003",
        "UMask": "0xc",
        "Unit": "cpu_core"
    },
    {
        "BriefDescription": "Execution stalls while L2 cache miss demand load is outstanding.",
        "Counter": "0,1,2,3",
        "CounterMask": "5",
        "EventCode": "0xa3",
        "EventName": "CYCLE_ACTIVITY.STALLS_L2_MISS",
        "SampleAfterValue": "1000003",
        "UMask": "0x5",
        "Unit": "cpu_core"
    },
    {
        "BriefDescription": "Total execution stalls.",
        "Counter": "0,1,2,3,4,5,6,7",
        "CounterMask": "4",
        "EventCode": "0xa3",
        "EventName": "CYCLE_ACTIVITY.STALLS_TOTAL",
        "SampleAfterValue": "1000003",
        "UMask": "0x4",
        "Unit": "cpu_core"
    },
    {
        "BriefDescription": "Cycles total of 1 uop is executed on all ports and Reservation Station was not empty.",
        "Counter": "0,1,2,3,4,5,6,7",
        "EventCode": "0xa6",
        "EventName": "EXE_ACTIVITY.1_PORTS_UTIL",
        "PublicDescription": "Counts cycles during which a total of 1 uop was executed on all ports and Reservation Station (RS) was not empty.",
        "SampleAfterValue": "2000003",
        "UMask": "0x2",
        "Unit": "cpu_core"
    },
    {
        "BriefDescription": "Cycles total of 2 or 3 uops are executed on all ports and Reservation Station (RS) was not empty.",
        "Counter": "0,1,2,3,4,5,6,7",
        "EventCode": "0xa6",
        "EventName": "EXE_ACTIVITY.2_3_PORTS_UTIL",
        "SampleAfterValue": "2000003",
        "UMask": "0xc",
        "Unit": "cpu_core"
    },
    {
        "BriefDescription": "Cycles total of 2 uops are executed on all ports and Reservation Station was not empty.",
        "Counter": "0,1,2,3,4,5,6,7",
        "EventCode": "0xa6",
        "EventName": "EXE_ACTIVITY.2_PORTS_UTIL",
        "PublicDescription": "Counts cycles during which a total of 2 uops were executed on all ports and Reservation Station (RS) was not empty.",
        "SampleAfterValue": "2000003",
        "UMask": "0x4",
        "Unit": "cpu_core"
    },
    {
        "BriefDescription": "Cycles total of 3 uops are executed on all ports and Reservation Station was not empty.",
        "Counter": "0,1,2,3,4,5,6,7",
        "EventCode": "0xa6",
        "EventName": "EXE_ACTIVITY.3_PORTS_UTIL",
        "PublicDescription": "Cycles total of 3 uops are executed on all ports and Reservation Station (RS) was not empty.",
        "SampleAfterValue": "2000003",
        "UMask": "0x8",
        "Unit": "cpu_core"
    },
    {
        "BriefDescription": "Cycles total of 4 uops are executed on all ports and Reservation Station was not empty.",
        "Counter": "0,1,2,3,4,5,6,7",
        "EventCode": "0xa6",
        "EventName": "EXE_ACTIVITY.4_PORTS_UTIL",
        "PublicDescription": "Cycles total of 4 uops are executed on all ports and Reservation Station (RS) was not empty.",
        "SampleAfterValue": "2000003",
        "UMask": "0x10",
        "Unit": "cpu_core"
    },
    {
        "BriefDescription": "Execution stalls while memory subsystem has an outstanding load.",
        "Counter": "0,1,2,3,4,5,6,7",
        "CounterMask": "5",
        "EventCode": "0xa6",
        "EventName": "EXE_ACTIVITY.BOUND_ON_LOADS",
        "SampleAfterValue": "2000003",
        "UMask": "0x21",
        "Unit": "cpu_core"
    },
    {
        "BriefDescription": "Cycles where the Store Buffer was full and no loads caused an execution stall.",
        "Counter": "0,1,2,3,4,5,6,7",
        "CounterMask": "2",
        "EventCode": "0xa6",
        "EventName": "EXE_ACTIVITY.BOUND_ON_STORES",
        "PublicDescription": "Counts cycles where the Store Buffer was full and no loads caused an execution stall.",
        "SampleAfterValue": "1000003",
        "UMask": "0x40",
        "Unit": "cpu_core"
    },
    {
        "BriefDescription": "Cycles no uop executed while RS was not empty, the SB was not full and there was no outstanding load.",
        "Counter": "0,1,2,3,4,5,6,7",
        "EventCode": "0xa6",
        "EventName": "EXE_ACTIVITY.EXE_BOUND_0_PORTS",
        "PublicDescription": "Number of cycles total of 0 uops executed on all ports, Reservation Station (RS) was not empty, the Store Buffer (SB) was not full and there was no outstanding load.",
        "SampleAfterValue": "1000003",
        "UMask": "0x80",
        "Unit": "cpu_core"
    },
    {
        "BriefDescription": "Instruction decoders utilized in a cycle",
        "Counter": "0,1,2,3",
        "EventCode": "0x75",
        "EventName": "INST_DECODED.DECODERS",
        "PublicDescription": "Number of decoders utilized in a cycle when the MITE (legacy decode pipeline) fetches instructions.",
        "SampleAfterValue": "2000003",
        "UMask": "0x1",
        "Unit": "cpu_core"
    },
    {
        "BriefDescription": "Counts the total number of instructions retired. (Fixed event)",
        "Counter": "Fixed counter 0",
        "EventName": "INST_RETIRED.ANY",
        "PublicDescription": "Counts the total number of instructions that retired. For instructions that consist of multiple uops, this event counts the retirement of the last uop of the instruction. This event continues counting during hardware interrupts, traps, and inside interrupt handlers. This event uses fixed counter 0. Available PDIST counters: 32",
        "SampleAfterValue": "2000003",
        "UMask": "0x1",
        "Unit": "cpu_atom"
    },
    {
        "BriefDescription": "Number of instructions retired. Fixed Counter - architectural event",
        "Counter": "Fixed counter 0",
        "EventName": "INST_RETIRED.ANY",
        "PublicDescription": "Counts the number of X86 instructions retired - an Architectural PerfMon event. Counting continues during hardware interrupts, traps, and inside interrupt handlers. Notes: INST_RETIRED.ANY is counted by a designated fixed counter freeing up programmable counters to count other events. INST_RETIRED.ANY_P is counted by a programmable counter. Available PDIST counters: 32",
        "SampleAfterValue": "2000003",
        "UMask": "0x1",
        "Unit": "cpu_core"
    },
    {
        "BriefDescription": "Counts the total number of instructions retired.",
        "Counter": "0,1,2,3,4,5",
        "EventCode": "0xc0",
        "EventName": "INST_RETIRED.ANY_P",
        "PublicDescription": "Counts the total number of instructions that retired. For instructions that consist of multiple uops, this event counts the retirement of the last uop of the instruction. This event continues counting during hardware interrupts, traps, and inside interrupt handlers. This event uses a programmable general purpose performance counter.",
        "SampleAfterValue": "2000003",
        "Unit": "cpu_atom"
    },
    {
        "BriefDescription": "Number of instructions retired. General Counter - architectural event",
        "Counter": "0,1,2,3,4,5,6,7",
        "EventCode": "0xc0",
        "EventName": "INST_RETIRED.ANY_P",
        "PublicDescription": "Counts the number of X86 instructions retired - an Architectural PerfMon event. Counting continues during hardware interrupts, traps, and inside interrupt handlers. Notes: INST_RETIRED.ANY is counted by a designated fixed counter freeing up programmable counters to count other events. INST_RETIRED.ANY_P is counted by a programmable counter.",
        "SampleAfterValue": "2000003",
        "Unit": "cpu_core"
    },
    {
        "BriefDescription": "INST_RETIRED.MACRO_FUSED",
        "Counter": "0,1,2,3,4,5,6,7",
        "EventCode": "0xc0",
        "EventName": "INST_RETIRED.MACRO_FUSED",
        "SampleAfterValue": "2000003",
        "UMask": "0x10",
        "Unit": "cpu_core"
    },
    {
        "BriefDescription": "Retired NOP instructions.",
        "Counter": "0,1,2,3,4,5,6,7",
        "EventCode": "0xc0",
        "EventName": "INST_RETIRED.NOP",
        "PublicDescription": "Counts all retired NOP or ENDBR32/64 instructions",
        "SampleAfterValue": "2000003",
        "UMask": "0x2",
        "Unit": "cpu_core"
    },
    {
        "BriefDescription": "Precise instruction retired with PEBS precise-distribution",
        "Counter": "Fixed counter 0",
        "EventName": "INST_RETIRED.PREC_DIST",
        "PublicDescription": "A version of INST_RETIRED that allows for a precise distribution of samples across instructions retired. It utilizes the Precise Distribution of Instructions Retired (PDIR++) feature to fix bias in how retired instructions get sampled. Use on Fixed Counter 0. Available PDIST counters: 32",
        "SampleAfterValue": "2000003",
        "UMask": "0x1",
        "Unit": "cpu_core"
    },
    {
        "BriefDescription": "Iterations of Repeat string retired instructions.",
        "Counter": "0,1,2,3,4,5,6,7",
        "EventCode": "0xc0",
        "EventName": "INST_RETIRED.REP_ITERATION",
        "PublicDescription": "Number of iterations of Repeat (REP) string retired instructions such as MOVS, CMPS, and SCAS. Each has a byte, word, and doubleword version and string instructions can be repeated using a repetition prefix, REP, that allows their architectural execution to be repeated a number of times as specified by the RCX register. Note the number of iterations is implementation-dependent.",
        "SampleAfterValue": "2000003",
        "UMask": "0x8",
        "Unit": "cpu_core"
    },
    {
        "BriefDescription": "Clears speculative count",
        "Counter": "0,1,2,3,4,5,6,7",
        "CounterMask": "1",
        "EdgeDetect": "1",
        "EventCode": "0xad",
        "EventName": "INT_MISC.CLEARS_COUNT",
        "PublicDescription": "Counts the number of speculative clears due to any type of branch misprediction or machine clears",
        "SampleAfterValue": "500009",
        "UMask": "0x1",
        "Unit": "cpu_core"
    },
    {
        "BriefDescription": "Counts cycles after recovery from a branch misprediction or machine clear till the first uop is issued from the resteered path.",
        "Counter": "0,1,2,3,4,5,6,7",
        "EventCode": "0xad",
        "EventName": "INT_MISC.CLEAR_RESTEER_CYCLES",
        "PublicDescription": "Cycles after recovery from a branch misprediction or machine clear till the first uop is issued from the resteered path.",
        "SampleAfterValue": "500009",
        "UMask": "0x80",
        "Unit": "cpu_core"
    },
    {
        "BriefDescription": "Core cycles the allocator was stalled due to recovery from earlier clear event for this thread",
        "Counter": "0,1,2,3,4,5,6,7",
        "EventCode": "0xad",
        "EventName": "INT_MISC.RECOVERY_CYCLES",
        "PublicDescription": "Counts core cycles when the Resource allocator was stalled due to recovery from an earlier branch misprediction or machine clear event.",
        "SampleAfterValue": "500009",
        "UMask": "0x1",
        "Unit": "cpu_core"
    },
    {
        "BriefDescription": "Bubble cycles of BAClear (Unknown Branch).",
        "Counter": "0,1,2,3,4,5,6,7",
        "EventCode": "0xad",
        "EventName": "INT_MISC.UNKNOWN_BRANCH_CYCLES",
        "MSRIndex": "0x3F7",
        "MSRValue": "0x7",
        "SampleAfterValue": "1000003",
        "UMask": "0x40",
        "Unit": "cpu_core"
    },
    {
        "BriefDescription": "TMA slots where uops got dropped",
        "Counter": "0,1,2,3,4,5,6,7",
        "EventCode": "0xad",
        "EventName": "INT_MISC.UOP_DROPPING",
        "PublicDescription": "Estimated number of Top-down Microarchitecture Analysis slots that got dropped due to non front-end reasons",
        "SampleAfterValue": "1000003",
        "UMask": "0x10",
        "Unit": "cpu_core"
    },
    {
        "BriefDescription": "INT_VEC_RETIRED.128BIT",
        "Counter": "0,1,2,3,4,5,6,7",
        "EventCode": "0xe7",
        "EventName": "INT_VEC_RETIRED.128BIT",
        "SampleAfterValue": "1000003",
        "UMask": "0x13",
        "Unit": "cpu_core"
    },
    {
        "BriefDescription": "INT_VEC_RETIRED.256BIT",
        "Counter": "0,1,2,3,4,5,6,7",
        "EventCode": "0xe7",
        "EventName": "INT_VEC_RETIRED.256BIT",
        "SampleAfterValue": "1000003",
        "UMask": "0xac",
        "Unit": "cpu_core"
    },
    {
        "BriefDescription": "integer ADD, SUB, SAD 128-bit vector instructions.",
        "Counter": "0,1,2,3,4,5,6,7",
        "EventCode": "0xe7",
        "EventName": "INT_VEC_RETIRED.ADD_128",
        "PublicDescription": "Number of retired integer ADD/SUB (regular or horizontal), SAD 128-bit vector instructions.",
        "SampleAfterValue": "1000003",
        "UMask": "0x3",
        "Unit": "cpu_core"
    },
    {
        "BriefDescription": "integer ADD, SUB, SAD 256-bit vector instructions.",
        "Counter": "0,1,2,3,4,5,6,7",
        "EventCode": "0xe7",
        "EventName": "INT_VEC_RETIRED.ADD_256",
        "PublicDescription": "Number of retired integer ADD/SUB (regular or horizontal), SAD 256-bit vector instructions.",
        "SampleAfterValue": "1000003",
        "UMask": "0xc",
        "Unit": "cpu_core"
    },
    {
        "BriefDescription": "INT_VEC_RETIRED.MUL_256",
        "Counter": "0,1,2,3,4,5,6,7",
        "EventCode": "0xe7",
        "EventName": "INT_VEC_RETIRED.MUL_256",
        "SampleAfterValue": "1000003",
        "UMask": "0x80",
        "Unit": "cpu_core"
    },
    {
        "BriefDescription": "INT_VEC_RETIRED.SHUFFLES",
        "Counter": "0,1,2,3,4,5,6,7",
        "EventCode": "0xe7",
        "EventName": "INT_VEC_RETIRED.SHUFFLES",
        "SampleAfterValue": "1000003",
        "UMask": "0x40",
        "Unit": "cpu_core"
    },
    {
        "BriefDescription": "INT_VEC_RETIRED.VNNI_128",
        "Counter": "0,1,2,3,4,5,6,7",
        "EventCode": "0xe7",
        "EventName": "INT_VEC_RETIRED.VNNI_128",
        "SampleAfterValue": "1000003",
        "UMask": "0x10",
        "Unit": "cpu_core"
    },
    {
        "BriefDescription": "INT_VEC_RETIRED.VNNI_256",
        "Counter": "0,1,2,3,4,5,6,7",
        "EventCode": "0xe7",
        "EventName": "INT_VEC_RETIRED.VNNI_256",
        "SampleAfterValue": "1000003",
        "UMask": "0x20",
        "Unit": "cpu_core"
    },
    {
        "BriefDescription": "This event is deprecated. Refer to new event LD_BLOCKS.ADDRESS_ALIAS",
        "Counter": "0,1,2,3,4,5",
        "Deprecated": "1",
        "EventCode": "0x03",
        "EventName": "LD_BLOCKS.4K_ALIAS",
        "SampleAfterValue": "1000003",
        "UMask": "0x4",
        "Unit": "cpu_atom"
    },
    {
        "BriefDescription": "Counts the number of retired loads that are blocked because it initially appears to be store forward blocked, but subsequently is shown not to be blocked based on 4K alias check.",
        "Counter": "0,1,2,3,4,5",
        "EventCode": "0x03",
        "EventName": "LD_BLOCKS.ADDRESS_ALIAS",
        "SampleAfterValue": "1000003",
        "UMask": "0x4",
        "Unit": "cpu_atom"
    },
    {
        "BriefDescription": "False dependencies in MOB due to partial compare on address.",
        "Counter": "0,1,2,3",
        "EventCode": "0x03",
        "EventName": "LD_BLOCKS.ADDRESS_ALIAS",
        "PublicDescription": "Counts the number of times a load got blocked due to false dependencies in MOB due to partial compare on address.",
        "SampleAfterValue": "100003",
        "UMask": "0x4",
        "Unit": "cpu_core"
    },
    {
        "BriefDescription": "Counts the number of retired loads that are blocked because its address exactly matches an older store whose data is not ready.",
        "Counter": "0,1,2,3,4,5",
        "EventCode": "0x03",
        "EventName": "LD_BLOCKS.DATA_UNKNOWN",
        "SampleAfterValue": "1000003",
        "UMask": "0x1",
        "Unit": "cpu_atom"
    },
    {
        "BriefDescription": "The number of times that split load operations are temporarily blocked because all resources for handling the split accesses are in use.",
        "Counter": "0,1,2,3",
        "EventCode": "0x03",
        "EventName": "LD_BLOCKS.NO_SR",
        "PublicDescription": "Counts the number of times that split load operations are temporarily blocked because all resources for handling the split accesses are in use.",
        "SampleAfterValue": "100003",
        "UMask": "0x88",
        "Unit": "cpu_core"
    },
    {
        "BriefDescription": "Loads blocked due to overlapping with a preceding store that cannot be forwarded.",
        "Counter": "0,1,2,3",
        "EventCode": "0x03",
        "EventName": "LD_BLOCKS.STORE_FORWARD",
        "PublicDescription": "Counts the number of times where store forwarding was prevented for a load operation. The most common case is a load blocked due to the address of memory access (partially) overlapping with a preceding uncompleted store. Note: See the table of not supported store forwards in the Optimization Guide.",
        "SampleAfterValue": "100003",
        "UMask": "0x82",
        "Unit": "cpu_core"
    },
    {
        "BriefDescription": "Counts the number of demand load dispatches that hit L1D fill buffer (FB) allocated for software prefetch.",
        "Counter": "0,1,2,3",
        "EventCode": "0x4c",
        "EventName": "LOAD_HIT_PREFETCH.SWPF",
        "PublicDescription": "Counts all software-prefetch load dispatches that hit the fill buffer (FB) allocated for the software prefetch. It can also be incremented by some lock instructions. So it should only be used with profiling so that the locks can be excluded by ASM (Assembly File) inspection of the nearby instructions.",
        "SampleAfterValue": "100003",
        "UMask": "0x1",
        "Unit": "cpu_core"
    },
    {
        "BriefDescription": "Cycles Uops delivered by the LSD, but didn't come from the decoder.",
        "Counter": "0,1,2,3,4,5,6,7",
        "CounterMask": "1",
        "EventCode": "0xa8",
        "EventName": "LSD.CYCLES_ACTIVE",
        "PublicDescription": "Counts the cycles when at least one uop is delivered by the LSD (Loop-stream detector).",
        "SampleAfterValue": "2000003",
        "UMask": "0x1",
        "Unit": "cpu_core"
    },
    {
        "BriefDescription": "Cycles optimal number of Uops delivered by the LSD, but did not come from the decoder.",
        "Counter": "0,1,2,3,4,5,6,7",
        "CounterMask": "6",
        "EventCode": "0xa8",
        "EventName": "LSD.CYCLES_OK",
        "PublicDescription": "Counts the cycles when optimal number of uops is delivered by the LSD (Loop-stream detector).",
        "SampleAfterValue": "2000003",
        "UMask": "0x1",
        "Unit": "cpu_core"
    },
    {
        "BriefDescription": "Number of Uops delivered by the LSD.",
        "Counter": "0,1,2,3,4,5,6,7",
        "EventCode": "0xa8",
        "EventName": "LSD.UOPS",
        "PublicDescription": "Counts the number of uops delivered to the back-end by the LSD(Loop Stream Detector).",
        "SampleAfterValue": "2000003",
        "UMask": "0x1",
        "Unit": "cpu_core"
    },
    {
        "BriefDescription": "Number of machine clears (nukes) of any type.",
        "Counter": "0,1,2,3,4,5,6,7",
        "CounterMask": "1",
        "EdgeDetect": "1",
        "EventCode": "0xc3",
        "EventName": "MACHINE_CLEARS.COUNT",
        "PublicDescription": "Counts the number of machine clears (nukes) of any type.",
        "SampleAfterValue": "100003",
        "UMask": "0x1",
        "Unit": "cpu_core"
    },
    {
        "BriefDescription": "Counts the number of machine clears due to memory ordering in which an internal load passes an older store within the same CPU.",
        "Counter": "0,1,2,3,4,5",
        "EventCode": "0xc3",
        "EventName": "MACHINE_CLEARS.DISAMBIGUATION",
        "SampleAfterValue": "20003",
        "UMask": "0x8",
        "Unit": "cpu_atom"
    },
    {
        "BriefDescription": "Counts the number of machines clears due to memory renaming.",
        "Counter": "0,1,2,3,4,5",
        "EventCode": "0xc3",
        "EventName": "MACHINE_CLEARS.MRN_NUKE",
        "SampleAfterValue": "1000003",
        "UMask": "0x80",
        "Unit": "cpu_atom"
    },
    {
        "BriefDescription": "Counts the number of machine clears due to a page fault.  Counts both I-Side and D-Side (Loads/Stores) page faults.  A page fault occurs when either the page is not present, or an access violation occurs.",
        "Counter": "0,1,2,3,4,5",
        "EventCode": "0xc3",
        "EventName": "MACHINE_CLEARS.PAGE_FAULT",
        "SampleAfterValue": "20003",
        "UMask": "0x20",
        "Unit": "cpu_atom"
    },
    {
        "BriefDescription": "This event is deprecated.",
        "Counter": "0,1,2,3,4,5",
        "Deprecated": "1",
        "EventCode": "0xc3",
        "EventName": "MACHINE_CLEARS.SLOW",
        "SampleAfterValue": "20003",
        "UMask": "0x6f",
        "Unit": "cpu_atom"
    },
    {
        "BriefDescription": "Counts the number of machine clears due to program modifying data (self modifying code) within 1K of a recently fetched code page.",
        "Counter": "0,1,2,3,4,5",
        "EventCode": "0xc3",
        "EventName": "MACHINE_CLEARS.SMC",
        "SampleAfterValue": "20003",
        "UMask": "0x1",
        "Unit": "cpu_atom"
    },
    {
        "BriefDescription": "Self-modifying code (SMC) detected.",
        "Counter": "0,1,2,3,4,5,6,7",
        "EventCode": "0xc3",
        "EventName": "MACHINE_CLEARS.SMC",
        "PublicDescription": "Counts self-modifying code (SMC) detected, which causes a machine clear.",
        "SampleAfterValue": "100003",
        "UMask": "0x4",
        "Unit": "cpu_core"
    },
    {
        "BriefDescription": "LFENCE instructions retired",
        "Counter": "0,1,2,3,4,5,6,7",
        "EventCode": "0xe0",
        "EventName": "MISC2_RETIRED.LFENCE",
        "PublicDescription": "number of LFENCE retired instructions",
        "SampleAfterValue": "400009",
        "UMask": "0x20",
        "Unit": "cpu_core"
    },
    {
        "BriefDescription": "Counts the number of LBR entries recorded. Requires LBRs to be enabled in IA32_LBR_CTL. [This event is alias to LBR_INSERTS.ANY]",
        "Counter": "0,1,2,3,4,5",
        "EventCode": "0xe4",
        "EventName": "MISC_RETIRED.LBR_INSERTS",
        "PublicDescription": "Counts the number of LBR entries recorded. Requires LBRs to be enabled in IA32_LBR_CTL. This event is PDIR on GP0 and NPEBS on all other GPs [This event is alias to LBR_INSERTS.ANY]",
        "SampleAfterValue": "1000003",
        "UMask": "0x1",
        "Unit": "cpu_atom"
    },
    {
        "BriefDescription": "Increments whenever there is an update to the LBR array.",
        "Counter": "0,1,2,3,4,5,6,7",
        "EventCode": "0xcc",
        "EventName": "MISC_RETIRED.LBR_INSERTS",
        "PublicDescription": "Increments when an entry is added to the Last Branch Record (LBR) array (or removed from the array in case of RETURNs in call stack mode). The event requires LBR enable via IA32_DEBUGCTL MSR and branch type selection via MSR_LBR_SELECT.",
        "SampleAfterValue": "100003",
        "UMask": "0x20",
        "Unit": "cpu_core"
    },
    {
        "BriefDescription": "Cycles stalled due to no store buffers available. (not including draining form sync).",
        "Counter": "0,1,2,3,4,5,6,7",
        "EventCode": "0xa2",
        "EventName": "RESOURCE_STALLS.SB",
        "PublicDescription": "Counts allocation stall cycles caused by the store buffer (SB) being full. This counts cycles that the pipeline back-end blocked uop delivery from the front-end.",
        "SampleAfterValue": "100003",
        "UMask": "0x8",
        "Unit": "cpu_core"
    },
    {
        "BriefDescription": "Counts cycles where the pipeline is stalled due to serializing operations.",
        "Counter": "0,1,2,3,4,5,6,7",
        "EventCode": "0xa2",
        "EventName": "RESOURCE_STALLS.SCOREBOARD",
        "SampleAfterValue": "100003",
        "UMask": "0x2",
        "Unit": "cpu_core"
    },
    {
        "BriefDescription": "Cycles when Reservation Station (RS) is empty for the thread.",
        "Counter": "0,1,2,3,4,5,6,7",
        "EventCode": "0xa5",
        "EventName": "RS.EMPTY",
        "PublicDescription": "Counts cycles during which the reservation station (RS) is empty for this logical processor. This is usually caused when the front-end pipeline runs into starvation periods (e.g. branch mispredictions or i-cache misses)",
        "SampleAfterValue": "1000003",
        "UMask": "0x7",
        "Unit": "cpu_core"
    },
    {
        "BriefDescription": "Counts end of periods where the Reservation Station (RS) was empty.",
        "Counter": "0,1,2,3,4,5,6,7",
        "CounterMask": "1",
        "EdgeDetect": "1",
        "EventCode": "0xa5",
        "EventName": "RS.EMPTY_COUNT",
        "Invert": "1",
        "PublicDescription": "Counts end of periods where the Reservation Station (RS) was empty. Could be useful to closely sample on front-end latency issues (see the FRONTEND_RETIRED event of designated precise events)",
        "SampleAfterValue": "100003",
        "UMask": "0x7",
        "Unit": "cpu_core"
    },
    {
        "BriefDescription": "Cycles when Reservation Station (RS) is empty due to a resource in the back-end",
        "Counter": "0,1,2,3,4,5,6,7",
        "EventCode": "0xa5",
        "EventName": "RS.EMPTY_RESOURCE",
        "SampleAfterValue": "1000003",
        "UMask": "0x1",
        "Unit": "cpu_core"
    },
    {
        "BriefDescription": "This event is deprecated. Refer to new event RS.EMPTY_COUNT",
        "Counter": "0,1,2,3,4,5,6,7",
        "CounterMask": "1",
        "Deprecated": "1",
        "EdgeDetect": "1",
        "EventCode": "0xa5",
        "EventName": "RS_EMPTY.COUNT",
        "Invert": "1",
        "SampleAfterValue": "100003",
        "UMask": "0x7",
        "Unit": "cpu_core"
    },
    {
        "BriefDescription": "This event is deprecated. Refer to new event RS.EMPTY",
        "Counter": "0,1,2,3,4,5,6,7",
        "Deprecated": "1",
        "EventCode": "0xa5",
        "EventName": "RS_EMPTY.CYCLES",
        "SampleAfterValue": "1000003",
        "UMask": "0x7",
        "Unit": "cpu_core"
    },
    {
        "BriefDescription": "Counts the number of issue slots in a UMWAIT or TPAUSE instruction where no uop issues due to the instruction putting the CPU into the C0.1 activity state. For Tremont, UMWAIT and TPAUSE will only put the CPU into C0.1 activity state (not C0.2 activity state)",
        "Counter": "0,1,2,3,4,5",
        "EventCode": "0x75",
        "EventName": "SERIALIZATION.C01_MS_SCB",
        "SampleAfterValue": "200003",
        "UMask": "0x4",
        "Unit": "cpu_atom"
    },
    {
        "BriefDescription": "Counts the number of issue slots not consumed by the backend due to a micro-sequencer (MS) scoreboard, which stalls the front-end from issuing from the UROM until a specified older uop retires.",
        "Counter": "0,1,2,3,4,5",
        "EventCode": "0x75",
        "EventName": "SERIALIZATION.NON_C01_MS_SCB",
        "PublicDescription": "Counts the number of issue slots not consumed by the backend due to a micro-sequencer (MS) scoreboard, which stalls the front-end from issuing from the UROM until a specified older uop retires. The most commonly executed instruction with an MS scoreboard is PAUSE.",
        "SampleAfterValue": "200003",
        "UMask": "0x2",
        "Unit": "cpu_atom"
    },
    {
        "BriefDescription": "TMA slots where no uops were being issued due to lack of back-end resources.",
        "Counter": "0,1,2,3,4,5,6,7",
        "EventCode": "0xa4",
        "EventName": "TOPDOWN.BACKEND_BOUND_SLOTS",
        "PublicDescription": "Number of slots in TMA method where no micro-operations were being issued from front-end to back-end of the machine due to lack of back-end resources.",
        "SampleAfterValue": "10000003",
        "UMask": "0x2",
        "Unit": "cpu_core"
    },
    {
        "BriefDescription": "TMA slots wasted due to incorrect speculations.",
        "Counter": "0",
        "EventCode": "0xa4",
        "EventName": "TOPDOWN.BAD_SPEC_SLOTS",
        "PublicDescription": "Number of slots of TMA method that were wasted due to incorrect speculation. It covers all types of control-flow or data-related mis-speculations.",
        "SampleAfterValue": "10000003",
        "UMask": "0x4",
        "Unit": "cpu_core"
    },
    {
        "BriefDescription": "TMA slots wasted due to incorrect speculation by branch mispredictions",
        "Counter": "0",
        "EventCode": "0xa4",
        "EventName": "TOPDOWN.BR_MISPREDICT_SLOTS",
        "PublicDescription": "Number of TMA slots that were wasted due to incorrect speculation by (any type of) branch mispredictions. This event estimates number of speculative operations that were issued but not retired as well as the out-of-order engine recovery past a branch misprediction.",
        "SampleAfterValue": "10000003",
        "UMask": "0x8",
        "Unit": "cpu_core"
    },
    {
        "BriefDescription": "TOPDOWN.MEMORY_BOUND_SLOTS",
        "Counter": "0,1,2,3,4,5,6,7",
        "EventCode": "0xa4",
        "EventName": "TOPDOWN.MEMORY_BOUND_SLOTS",
        "SampleAfterValue": "10000003",
        "UMask": "0x10",
        "Unit": "cpu_core"
    },
    {
        "BriefDescription": "TMA slots available for an unhalted logical processor. Fixed counter - architectural event",
        "Counter": "Fixed counter 3",
        "EventName": "TOPDOWN.SLOTS",
        "PublicDescription": "Number of available slots for an unhalted logical processor. The event increments by machine-width of the narrowest pipeline as employed by the Top-down Microarchitecture Analysis method (TMA). The count is distributed among unhalted logical processors (hyper-threads) who share the same physical core. Software can use this event as the denominator for the top-level metrics of the TMA method. This architectural event is counted on a designated fixed counter (Fixed Counter 3).",
        "SampleAfterValue": "10000003",
        "UMask": "0x4",
        "Unit": "cpu_core"
    },
    {
        "BriefDescription": "TMA slots available for an unhalted logical processor. General counter - architectural event",
        "Counter": "0,1,2,3,4,5,6,7",
        "EventCode": "0xa4",
        "EventName": "TOPDOWN.SLOTS_P",
        "PublicDescription": "Counts the number of available slots for an unhalted logical processor. The event increments by machine-width of the narrowest pipeline as employed by the Top-down Microarchitecture Analysis method. The count is distributed among unhalted logical processors (hyper-threads) who share the same physical core.",
        "SampleAfterValue": "10000003",
        "UMask": "0x1",
        "Unit": "cpu_core"
    },
    {
        "BriefDescription": "Counts the total number of issue slots that were not consumed by the backend because allocation is stalled due to a mispredicted jump or a machine clear.",
        "Counter": "0,1,2,3,4,5",
        "EventCode": "0x73",
        "EventName": "TOPDOWN_BAD_SPECULATION.ALL",
        "PublicDescription": "Counts the total number of issue slots that were not consumed by the backend because allocation is stalled due to a mispredicted jump or a machine clear. Only issue slots wasted due to fast nukes such as memory ordering nukes are counted. Other nukes are not accounted for. Counts all issue slots blocked during this recovery window including relevant microcode flows and while uops are not yet available in the instruction queue (IQ) even if an FE_bound event occurs during this period. Also includes the issue slots that were consumed by the backend but were thrown away because they were younger than the mispredict or machine clear.",
        "SampleAfterValue": "1000003",
        "Unit": "cpu_atom"
    },
    {
        "BriefDescription": "Counts the number of issue slots every cycle that were not consumed by the backend due to fast nukes such as memory ordering and memory disambiguation machine clears.",
        "Counter": "0,1,2,3,4,5",
        "EventCode": "0x73",
        "EventName": "TOPDOWN_BAD_SPECULATION.FASTNUKE",
        "SampleAfterValue": "1000003",
        "UMask": "0x2",
        "Unit": "cpu_atom"
    },
    {
        "BriefDescription": "Counts the total number of issue slots that were not consumed by the backend because allocation is stalled due to a machine clear (nuke) of any kind including memory ordering and memory disambiguation.",
        "Counter": "0,1,2,3,4,5",
        "EventCode": "0x73",
        "EventName": "TOPDOWN_BAD_SPECULATION.MACHINE_CLEARS",
        "SampleAfterValue": "1000003",
        "UMask": "0x3",
        "Unit": "cpu_atom"
    },
    {
        "BriefDescription": "Counts the number of issue slots every cycle that were not consumed by the backend due to branch mispredicts.",
        "Counter": "0,1,2,3,4,5",
        "EventCode": "0x73",
        "EventName": "TOPDOWN_BAD_SPECULATION.MISPREDICT",
        "SampleAfterValue": "1000003",
        "UMask": "0x4",
        "Unit": "cpu_atom"
    },
    {
        "BriefDescription": "Counts the number of issue slots every cycle that were not consumed by the backend due to a machine clear (nuke).",
        "Counter": "0,1,2,3,4,5",
        "EventCode": "0x73",
        "EventName": "TOPDOWN_BAD_SPECULATION.NUKE",
        "SampleAfterValue": "1000003",
        "UMask": "0x1",
        "Unit": "cpu_atom"
    },
    {
        "BriefDescription": "Counts the total number of issue slots every cycle that were not consumed by the backend due to backend stalls.",
        "Counter": "0,1,2,3,4,5",
        "EventCode": "0x74",
        "EventName": "TOPDOWN_BE_BOUND.ALL",
        "SampleAfterValue": "1000003",
        "Unit": "cpu_atom"
    },
    {
        "BriefDescription": "Counts the number of issue slots every cycle that were not consumed by the backend due to certain allocation restrictions.",
        "Counter": "0,1,2,3,4,5",
        "EventCode": "0x74",
        "EventName": "TOPDOWN_BE_BOUND.ALLOC_RESTRICTIONS",
        "SampleAfterValue": "1000003",
        "UMask": "0x1",
        "Unit": "cpu_atom"
    },
    {
        "BriefDescription": "Counts the number of issue slots every cycle that were not consumed by the backend due to memory reservation stalls in which a scheduler is not able to accept uops.",
        "Counter": "0,1,2,3,4,5",
        "EventCode": "0x74",
        "EventName": "TOPDOWN_BE_BOUND.MEM_SCHEDULER",
        "SampleAfterValue": "1000003",
        "UMask": "0x2",
        "Unit": "cpu_atom"
    },
    {
        "BriefDescription": "Counts the number of issue slots every cycle that were not consumed by the backend due to IEC or FPC RAT stalls, which can be due to FIQ or IEC reservation stalls in which the integer, floating point or SIMD scheduler is not able to accept uops.",
        "Counter": "0,1,2,3,4,5",
        "EventCode": "0x74",
        "EventName": "TOPDOWN_BE_BOUND.NON_MEM_SCHEDULER",
        "SampleAfterValue": "1000003",
        "UMask": "0x8",
        "Unit": "cpu_atom"
    },
    {
        "BriefDescription": "Counts the number of issue slots every cycle that were not consumed by the backend due to the physical register file unable to accept an entry (marble stalls).",
        "Counter": "0,1,2,3,4,5",
        "EventCode": "0x74",
        "EventName": "TOPDOWN_BE_BOUND.REGISTER",
        "SampleAfterValue": "1000003",
        "UMask": "0x20",
        "Unit": "cpu_atom"
    },
    {
        "BriefDescription": "Counts the number of issue slots every cycle that were not consumed by the backend due to the reorder buffer being full (ROB stalls).",
        "Counter": "0,1,2,3,4,5",
        "EventCode": "0x74",
        "EventName": "TOPDOWN_BE_BOUND.REORDER_BUFFER",
        "SampleAfterValue": "1000003",
        "UMask": "0x40",
        "Unit": "cpu_atom"
    },
    {
        "BriefDescription": "Counts the number of issue slots every cycle that were not consumed by the backend due to scoreboards from the instruction queue (IQ), jump execution unit (JEU), or microcode sequencer (MS).",
        "Counter": "0,1,2,3,4,5",
        "EventCode": "0x74",
        "EventName": "TOPDOWN_BE_BOUND.SERIALIZATION",
        "SampleAfterValue": "1000003",
        "UMask": "0x10",
        "Unit": "cpu_atom"
    },
    {
        "BriefDescription": "Counts the total number of issue slots every cycle that were not consumed by the backend due to frontend stalls.",
        "Counter": "0,1,2,3,4,5",
        "EventCode": "0x71",
        "EventName": "TOPDOWN_FE_BOUND.ALL",
        "SampleAfterValue": "1000003",
        "Unit": "cpu_atom"
    },
    {
        "BriefDescription": "Counts the number of issue slots every cycle that were not delivered by the frontend due to BACLEARS.",
        "Counter": "0,1,2,3,4,5",
        "EventCode": "0x71",
        "EventName": "TOPDOWN_FE_BOUND.BRANCH_DETECT",
        "PublicDescription": "Counts the number of issue slots every cycle that were not delivered by the frontend due to BACLEARS, which occurs when the Branch Target Buffer (BTB) prediction or lack thereof, was corrected by a later branch predictor in the frontend. Includes BACLEARS due to all branch types including conditional and unconditional jumps, returns, and indirect branches.",
        "SampleAfterValue": "1000003",
        "UMask": "0x2",
        "Unit": "cpu_atom"
    },
    {
        "BriefDescription": "Counts the number of issue slots every cycle that were not delivered by the frontend due to BTCLEARS.",
        "Counter": "0,1,2,3,4,5",
        "EventCode": "0x71",
        "EventName": "TOPDOWN_FE_BOUND.BRANCH_RESTEER",
        "PublicDescription": "Counts the number of issue slots every cycle that were not delivered by the frontend due to BTCLEARS, which occurs when the Branch Target Buffer (BTB) predicts a taken branch.",
        "SampleAfterValue": "1000003",
        "UMask": "0x40",
        "Unit": "cpu_atom"
    },
    {
        "BriefDescription": "Counts the number of issue slots every cycle that were not delivered by the frontend due to the microcode sequencer (MS).",
        "Counter": "0,1,2,3,4,5",
        "EventCode": "0x71",
        "EventName": "TOPDOWN_FE_BOUND.CISC",
        "SampleAfterValue": "1000003",
        "UMask": "0x1",
        "Unit": "cpu_atom"
    },
    {
        "BriefDescription": "Counts the number of issue slots every cycle that were not delivered by the frontend due to decode stalls.",
        "Counter": "0,1,2,3,4,5",
        "EventCode": "0x71",
        "EventName": "TOPDOWN_FE_BOUND.DECODE",
        "SampleAfterValue": "1000003",
        "UMask": "0x8",
        "Unit": "cpu_atom"
    },
    {
        "BriefDescription": "Counts the number of issue slots every cycle that were not delivered by the frontend due to frontend bandwidth restrictions due to decode, predecode, cisc, and other limitations.",
        "Counter": "0,1,2,3,4,5",
        "EventCode": "0x71",
        "EventName": "TOPDOWN_FE_BOUND.FRONTEND_BANDWIDTH",
        "SampleAfterValue": "1000003",
        "UMask": "0x8d",
        "Unit": "cpu_atom"
    },
    {
        "BriefDescription": "Counts the number of issue slots every cycle that were not delivered by the frontend due to a latency related stalls including BACLEARs, BTCLEARs, ITLB misses, and ICache misses.",
        "Counter": "0,1,2,3,4,5",
        "EventCode": "0x71",
        "EventName": "TOPDOWN_FE_BOUND.FRONTEND_LATENCY",
        "SampleAfterValue": "1000003",
        "UMask": "0x72",
        "Unit": "cpu_atom"
    },
    {
        "BriefDescription": "Counts the number of issue slots every cycle that were not delivered by the frontend due to ITLB misses.",
        "Counter": "0,1,2,3,4,5",
        "EventCode": "0x71",
        "EventName": "TOPDOWN_FE_BOUND.ITLB",
        "PublicDescription": "Counts the number of issue slots every cycle that were not delivered by the frontend due to Instruction Table Lookaside Buffer (ITLB) misses.",
        "SampleAfterValue": "1000003",
        "UMask": "0x10",
        "Unit": "cpu_atom"
    },
    {
        "BriefDescription": "Counts the number of issue slots every cycle that were not delivered by the frontend due to other common frontend stalls not categorized.",
        "Counter": "0,1,2,3,4,5",
        "EventCode": "0x71",
        "EventName": "TOPDOWN_FE_BOUND.OTHER",
        "SampleAfterValue": "1000003",
        "UMask": "0x80",
        "Unit": "cpu_atom"
    },
    {
        "BriefDescription": "Counts the number of issue slots every cycle that were not delivered by the frontend due to wrong predecodes.",
        "Counter": "0,1,2,3,4,5",
        "EventCode": "0x71",
        "EventName": "TOPDOWN_FE_BOUND.PREDECODE",
        "SampleAfterValue": "1000003",
        "UMask": "0x4",
        "Unit": "cpu_atom"
    },
    {
        "BriefDescription": "Counts the total number of consumed retirement slots.",
        "Counter": "0,1,2,3,4,5",
        "EventCode": "0xc2",
        "EventName": "TOPDOWN_RETIRING.ALL",
        "SampleAfterValue": "1000003",
        "Unit": "cpu_atom"
    },
    {
        "BriefDescription": "UOPS_DECODED.DEC0_UOPS",
        "Counter": "0,1,2,3",
        "EventCode": "0x76",
        "EventName": "UOPS_DECODED.DEC0_UOPS",
        "SampleAfterValue": "1000003",
        "UMask": "0x1",
        "Unit": "cpu_core"
    },
    {
        "BriefDescription": "Uops executed on port 0",
        "Counter": "0,1,2,3,4,5,6,7",
        "EventCode": "0xb2",
        "EventName": "UOPS_DISPATCHED.PORT_0",
        "PublicDescription": "Number of uops dispatch to execution  port 0.",
        "SampleAfterValue": "2000003",
        "UMask": "0x1",
        "Unit": "cpu_core"
    },
    {
        "BriefDescription": "Uops executed on port 1",
        "Counter": "0,1,2,3,4,5,6,7",
        "EventCode": "0xb2",
        "EventName": "UOPS_DISPATCHED.PORT_1",
        "PublicDescription": "Number of uops dispatch to execution  port 1.",
        "SampleAfterValue": "2000003",
        "UMask": "0x2",
        "Unit": "cpu_core"
    },
    {
        "BriefDescription": "Uops executed on ports 2, 3 and 10",
        "Counter": "0,1,2,3,4,5,6,7",
        "EventCode": "0xb2",
        "EventName": "UOPS_DISPATCHED.PORT_2_3_10",
        "PublicDescription": "Number of uops dispatch to execution ports 2, 3 and 10",
        "SampleAfterValue": "2000003",
        "UMask": "0x4",
        "Unit": "cpu_core"
    },
    {
        "BriefDescription": "Uops executed on ports 4 and 9",
        "Counter": "0,1,2,3,4,5,6,7",
        "EventCode": "0xb2",
        "EventName": "UOPS_DISPATCHED.PORT_4_9",
        "PublicDescription": "Number of uops dispatch to execution ports 4 and 9",
        "SampleAfterValue": "2000003",
        "UMask": "0x10",
        "Unit": "cpu_core"
    },
    {
        "BriefDescription": "Uops executed on ports 5 and 11",
        "Counter": "0,1,2,3,4,5,6,7",
        "EventCode": "0xb2",
        "EventName": "UOPS_DISPATCHED.PORT_5_11",
        "PublicDescription": "Number of uops dispatch to execution ports 5 and 11",
        "SampleAfterValue": "2000003",
        "UMask": "0x20",
        "Unit": "cpu_core"
    },
    {
        "BriefDescription": "Uops executed on port 6",
        "Counter": "0,1,2,3,4,5,6,7",
        "EventCode": "0xb2",
        "EventName": "UOPS_DISPATCHED.PORT_6",
        "PublicDescription": "Number of uops dispatch to execution  port 6.",
        "SampleAfterValue": "2000003",
        "UMask": "0x40",
        "Unit": "cpu_core"
    },
    {
        "BriefDescription": "Uops executed on ports 7 and 8",
        "Counter": "0,1,2,3,4,5,6,7",
        "EventCode": "0xb2",
        "EventName": "UOPS_DISPATCHED.PORT_7_8",
        "PublicDescription": "Number of uops dispatch to execution  ports 7 and 8.",
        "SampleAfterValue": "2000003",
        "UMask": "0x80",
        "Unit": "cpu_core"
    },
    {
        "BriefDescription": "Cycles at least 1 micro-op is executed from any thread on physical core.",
        "Counter": "0,1,2,3,4,5,6,7",
        "CounterMask": "1",
        "EventCode": "0xb1",
        "EventName": "UOPS_EXECUTED.CORE_CYCLES_GE_1",
        "PublicDescription": "Counts cycles when at least 1 micro-op is executed from any thread on physical core.",
        "SampleAfterValue": "2000003",
        "UMask": "0x2",
        "Unit": "cpu_core"
    },
    {
        "BriefDescription": "Cycles at least 2 micro-op is executed from any thread on physical core.",
        "Counter": "0,1,2,3,4,5,6,7",
        "CounterMask": "2",
        "EventCode": "0xb1",
        "EventName": "UOPS_EXECUTED.CORE_CYCLES_GE_2",
        "PublicDescription": "Counts cycles when at least 2 micro-ops are executed from any thread on physical core.",
        "SampleAfterValue": "2000003",
        "UMask": "0x2",
        "Unit": "cpu_core"
    },
    {
        "BriefDescription": "Cycles at least 3 micro-op is executed from any thread on physical core.",
        "Counter": "0,1,2,3,4,5,6,7",
        "CounterMask": "3",
        "EventCode": "0xb1",
        "EventName": "UOPS_EXECUTED.CORE_CYCLES_GE_3",
        "PublicDescription": "Counts cycles when at least 3 micro-ops are executed from any thread on physical core.",
        "SampleAfterValue": "2000003",
        "UMask": "0x2",
        "Unit": "cpu_core"
    },
    {
        "BriefDescription": "Cycles at least 4 micro-op is executed from any thread on physical core.",
        "Counter": "0,1,2,3,4,5,6,7",
        "CounterMask": "4",
        "EventCode": "0xb1",
        "EventName": "UOPS_EXECUTED.CORE_CYCLES_GE_4",
        "PublicDescription": "Counts cycles when at least 4 micro-ops are executed from any thread on physical core.",
        "SampleAfterValue": "2000003",
        "UMask": "0x2",
        "Unit": "cpu_core"
    },
    {
        "BriefDescription": "Cycles where at least 1 uop was executed per-thread",
        "Counter": "0,1,2,3,4,5,6,7",
        "CounterMask": "1",
        "EventCode": "0xb1",
        "EventName": "UOPS_EXECUTED.CYCLES_GE_1",
        "PublicDescription": "Cycles where at least 1 uop was executed per-thread.",
        "SampleAfterValue": "2000003",
        "UMask": "0x1",
        "Unit": "cpu_core"
    },
    {
        "BriefDescription": "Cycles where at least 2 uops were executed per-thread",
        "Counter": "0,1,2,3,4,5,6,7",
        "CounterMask": "2",
        "EventCode": "0xb1",
        "EventName": "UOPS_EXECUTED.CYCLES_GE_2",
        "PublicDescription": "Cycles where at least 2 uops were executed per-thread.",
        "SampleAfterValue": "2000003",
        "UMask": "0x1",
        "Unit": "cpu_core"
    },
    {
        "BriefDescription": "Cycles where at least 3 uops were executed per-thread",
        "Counter": "0,1,2,3,4,5,6,7",
        "CounterMask": "3",
        "EventCode": "0xb1",
        "EventName": "UOPS_EXECUTED.CYCLES_GE_3",
        "PublicDescription": "Cycles where at least 3 uops were executed per-thread.",
        "SampleAfterValue": "2000003",
        "UMask": "0x1",
        "Unit": "cpu_core"
    },
    {
        "BriefDescription": "Cycles where at least 4 uops were executed per-thread",
        "Counter": "0,1,2,3,4,5,6,7",
        "CounterMask": "4",
        "EventCode": "0xb1",
        "EventName": "UOPS_EXECUTED.CYCLES_GE_4",
        "PublicDescription": "Cycles where at least 4 uops were executed per-thread.",
        "SampleAfterValue": "2000003",
        "UMask": "0x1",
        "Unit": "cpu_core"
    },
    {
        "BriefDescription": "Counts number of cycles no uops were dispatched to be executed on this thread.",
        "Counter": "0,1,2,3,4,5,6,7",
        "CounterMask": "1",
        "EventCode": "0xb1",
        "EventName": "UOPS_EXECUTED.STALLS",
        "Invert": "1",
        "PublicDescription": "Counts cycles during which no uops were dispatched from the Reservation Station (RS) per thread.",
        "SampleAfterValue": "2000003",
        "UMask": "0x1",
        "Unit": "cpu_core"
    },
    {
        "BriefDescription": "This event is deprecated. Refer to new event UOPS_EXECUTED.STALLS",
        "Counter": "0,1,2,3,4,5,6,7",
        "CounterMask": "1",
        "Deprecated": "1",
        "EventCode": "0xb1",
        "EventName": "UOPS_EXECUTED.STALL_CYCLES",
        "Invert": "1",
        "SampleAfterValue": "2000003",
        "UMask": "0x1",
        "Unit": "cpu_core"
    },
    {
        "BriefDescription": "Counts the number of uops to be executed per-thread each cycle.",
        "Counter": "0,1,2,3,4,5,6,7",
        "EventCode": "0xb1",
        "EventName": "UOPS_EXECUTED.THREAD",
        "SampleAfterValue": "2000003",
        "UMask": "0x1",
        "Unit": "cpu_core"
    },
    {
        "BriefDescription": "Counts the number of x87 uops dispatched.",
        "Counter": "0,1,2,3,4,5,6,7",
        "EventCode": "0xb1",
        "EventName": "UOPS_EXECUTED.X87",
        "PublicDescription": "Counts the number of x87 uops executed.",
        "SampleAfterValue": "2000003",
        "UMask": "0x10",
        "Unit": "cpu_core"
    },
    {
        "BriefDescription": "Counts the number of uops issued by the front end every cycle.",
        "Counter": "0,1,2,3,4,5",
        "EventCode": "0x0e",
        "EventName": "UOPS_ISSUED.ANY",
        "PublicDescription": "Counts the number of uops issued by the front end every cycle. When 4-uops are requested and only 2-uops are delivered, the event counts 2.  Uops_issued correlates to the number of ROB entries.  If uop takes 2 ROB slots it counts as 2 uops_issued.",
        "SampleAfterValue": "200003",
        "Unit": "cpu_atom"
    },
    {
        "BriefDescription": "Uops that RAT issues to RS",
        "Counter": "0,1,2,3,4,5,6,7",
        "EventCode": "0xae",
        "EventName": "UOPS_ISSUED.ANY",
        "PublicDescription": "Counts the number of uops that the Resource Allocation Table (RAT) issues to the Reservation Station (RS).",
        "SampleAfterValue": "2000003",
        "UMask": "0x1",
        "Unit": "cpu_core"
    },
    {
        "BriefDescription": "UOPS_ISSUED.CYCLES",
        "Counter": "0,1,2,3,4,5,6,7",
        "CounterMask": "1",
        "EventCode": "0xae",
        "EventName": "UOPS_ISSUED.CYCLES",
        "SampleAfterValue": "2000003",
        "UMask": "0x1",
        "Unit": "cpu_core"
    },
    {
        "BriefDescription": "Counts the total number of uops retired.",
        "Counter": "0,1,2,3,4,5",
        "EventCode": "0xc2",
        "EventName": "UOPS_RETIRED.ALL",
        "SampleAfterValue": "2000003",
        "Unit": "cpu_atom"
    },
    {
        "BriefDescription": "Cycles with retired uop(s).",
        "Counter": "0,1,2,3,4,5,6,7",
        "CounterMask": "1",
        "EventCode": "0xc2",
        "EventName": "UOPS_RETIRED.CYCLES",
        "PublicDescription": "Counts cycles where at least one uop has retired.",
        "SampleAfterValue": "1000003",
        "UMask": "0x2",
        "Unit": "cpu_core"
    },
    {
        "BriefDescription": "Retired uops except the last uop of each instruction.",
        "Counter": "0,1,2,3,4,5,6,7",
        "EventCode": "0xc2",
        "EventName": "UOPS_RETIRED.HEAVY",
        "PublicDescription": "Counts the number of retired micro-operations (uops) except the last uop of each instruction. An instruction that is decoded into less than two uops does not contribute to the count.",
        "SampleAfterValue": "2000003",
        "UMask": "0x1",
        "Unit": "cpu_core"
    },
    {
        "BriefDescription": "Counts the number of integer divide uops retired.",
        "Counter": "0,1,2,3,4,5",
        "EventCode": "0xc2",
        "EventName": "UOPS_RETIRED.IDIV",
        "SampleAfterValue": "2000003",
        "UMask": "0x10",
        "Unit": "cpu_atom"
    },
    {
        "BriefDescription": "Counts the number of uops that are from complex flows issued by the micro-sequencer (MS).",
        "Counter": "0,1,2,3,4,5",
        "EventCode": "0xc2",
        "EventName": "UOPS_RETIRED.MS",
        "PublicDescription": "Counts the number of uops that are from complex flows issued by the Microcode Sequencer (MS). This includes uops from flows due to complex instructions, faults, assists, and inserted flows.",
        "SampleAfterValue": "2000003",
        "UMask": "0x1",
        "Unit": "cpu_atom"
    },
    {
        "BriefDescription": "UOPS_RETIRED.MS",
        "Counter": "0,1,2,3,4,5,6,7",
        "EventCode": "0xc2",
        "EventName": "UOPS_RETIRED.MS",
        "MSRIndex": "0x3F7",
        "MSRValue": "0x8",
        "SampleAfterValue": "2000003",
        "UMask": "0x4",
        "Unit": "cpu_core"
    },
    {
        "BriefDescription": "Retirement slots used.",
        "Counter": "0,1,2,3,4,5,6,7",
        "EventCode": "0xc2",
        "EventName": "UOPS_RETIRED.SLOTS",
        "PublicDescription": "Counts the retirement slots used each cycle.",
        "SampleAfterValue": "2000003",
        "UMask": "0x2",
        "Unit": "cpu_core"
    },
    {
        "BriefDescription": "Cycles without actually retired uops.",
        "Counter": "0,1,2,3,4,5,6,7",
        "CounterMask": "1",
        "EventCode": "0xc2",
        "EventName": "UOPS_RETIRED.STALLS",
        "Invert": "1",
        "PublicDescription": "This event counts cycles without actually retired uops.",
        "SampleAfterValue": "1000003",
        "UMask": "0x2",
        "Unit": "cpu_core"
    },
    {
        "BriefDescription": "This event is deprecated. Refer to new event UOPS_RETIRED.STALLS",
        "Counter": "0,1,2,3,4,5,6,7",
        "CounterMask": "1",
        "Deprecated": "1",
        "EventCode": "0xc2",
        "EventName": "UOPS_RETIRED.STALL_CYCLES",
        "Invert": "1",
        "SampleAfterValue": "1000003",
        "UMask": "0x2",
        "Unit": "cpu_core"
    },
    {
        "BriefDescription": "Counts the number of x87 uops retired, includes those in MS flows.",
        "Counter": "0,1,2,3,4,5",
        "EventCode": "0xc2",
        "EventName": "UOPS_RETIRED.X87",
        "SampleAfterValue": "2000003",
        "UMask": "0x2",
        "Unit": "cpu_atom"
    }
]
